{
  "$schema": "https://developer.microsoft.com/json-schemas/fabric/item/report/definition/visualContainer/2.6.0/schema.json",
  "name": "0128447c5565d8c1a209",
  "position": {
    "x": -2.2204460492503131E-16,
    "y": 429.6290359514532,
    "z": 13003,
    "height": 68.010075566750629,
    "width": 162.31738035264482,
    "tabOrder": 13003
  },
  "visual": {
    "visualType": "slicer",
    "query": {
      "queryState": {
        "Values": {
          "projections": [
            {
              "field": {
                "Column": {
                  "Expression": {
                    "SourceRef": {
                      "Entity": "superstore_limpo"
                    }
                  },
                  "Property": "region"
                }
              },
              "queryRef": "superstore_limpo.region",
              "nativeQueryRef": "Região",
              "active": true,
              "displayName": "Região"
            }
          ]
        }
      }
    },
    "objects": {
      "data": [
        {
          "properties": {
            "mode": {
              "expr": {
                "Literal": {
                  "Value": "'Dropdown'"
                }
              }
            }
          }
        }
      ]
    },
    "drillFilterOtherVisuals": true
  }
}